{
  "project_info": {
    "project_number": "867504915027",
    "project_id": "canteenorderingapp-de604",
    "storage_bucket": "canteenorderingapp-de604.firebasestorage.app"
  },
  "client": [
    {
      "client_info": {
        "mobilesdk_app_id": "1:867504915027:android:de1f6fae459bf68b2f3ca6",
        "android_client_info": {
          "package_name": "com.example.canteen_app"
        }
      },
      "oauth_client": [],
      "api_key": [
        {
          "current_key": "AIzaSyDSSgGIlSLjJnMbXUDOgEU3hPeJ1R7oUd8"
        }
      ],
      "services": {
        "appinvite_service": {
          "other_platform_oauth_client": []
        }
      }
    }
  ],
  "configuration_version": "1"
}